<Properties StartupConfiguration="{0F79FFD2-1FE6-4186-A055-DDC567664E64}|Default">
  <MonoDevelop.Ide.DebuggingService.PinnedWatches />
  <MultiItemStartupConfigurations />
  <MonoDevelop.Ide.Workspace ActiveConfiguration="Debug" />
  <MonoDevelop.Ide.Workbench ActiveDocument="fa22Team16/Controllers/StockPortfolioController.cs">
    <Files>
      <File FileName="fa22Team16/Controllers/StockTransactionController.cs" />
      <File FileName="fa22Team16/Views/StockTransaction/Create.cshtml" />
      <File FileName="fa22Team16/Models/StockTransaction.cs" />
      <File FileName="fa22Team16/Controllers/StockPortfolioController.cs" Line="89" Column="42" />
      <File FileName="fa22Team16/Seeding/SeedPortfolios.cs" />
      <File FileName="fa22Team16/Views/StockPortfolio/Index.cshtml" />
      <File FileName="fa22Team16/Models/StockPortfolio.cs" />
    </Files>
    <Pads>
      <Pad Id="ProjectPad">
        <State name="__root__">
          <Node name="fa22Team16" expanded="True">
            <Node name="fa22Team16" expanded="True">
              <Node name="Controllers" expanded="True" />
              <Node name="Models" expanded="True">
                <Node name="ViewModels" expanded="True" />
              </Node>
              <Node name="Properties" expanded="True" />
              <Node name="Seeding" expanded="True" />
              <Node name="Utilities" expanded="True" />
              <Node name="Views" expanded="True">
                <Node name="Account" expanded="True" />
                <Node name="BankAccount" expanded="True" />
                <Node name="Home" expanded="True" />
                <Node name="StockPortfolio" expanded="True" />
                <Node name="StockTransaction" expanded="True" />
              </Node>
            </Node>
          </Node>
        </State>
      </Pad>
    </Pads>
  </MonoDevelop.Ide.Workbench>
  <MonoDevelop.Ide.DebuggingService.Breakpoints>
    <BreakpointStore>
      <Breakpoint enabled="false" file="/Users/gkm/Documents/COLLEGE/semsters/Fall 2022/MIS333K/GitHub/MIS333K_FinalProject/fa22Team16/fa22Team16/Views/Dispute/Index.cshtml" relfile="fa22Team16/Views/Dispute/Index.cshtml" line="58" column="1" />
    </BreakpointStore>
  </MonoDevelop.Ide.DebuggingService.Breakpoints>
  <MonoDevelop.Ide.ItemProperties.fa22Team16 PreferredExecutionTarget="/Applications/Google Chrome.app" />
</Properties>